{"cameraMode":{"drawMode":0,"name":"Shaded","section":"Shading Mode"},"sceneLighting":true,"audioPlay":false,"sceneViewState":{"m_AlwaysRefresh":false,"showFog":true,"showSkybox":true,"showFlares":true,"showImageEffects":true,"showParticleSystems":true,"showVisualEffectGraphs":true,"m_FxEnabled":true},"in2DMode":false,"pivot":{"x":16.22929573059082,"y":-13.471681594848633,"z":6.154583930969238},"rotation":{"x":0.2643440365791321,"y":0.5523499846458435,"z":-0.19029738008975984,"w":0.7671905755996704},"size":12.461819648742676,"orthographic":false}